[
    {
        "nama" : "Bawang Merah",
        "satuan" : "siung"
    },
    {
        "nama" : "Bawang Putih",
        "satuan" : "siung"
    },
    {
        "nama" : "Royco Kaldu Ayam",
        "satuan" : "bungkus"
    },
    {
        "nama" : "Minyak Wijen",
        "satuan" : "sdm"
    },
    {
        "nama" : "Cabai Merah",
        "satuan" : "buah"
    },
    {
        "nama" : "Kangkung",
        "satuan" : "ikat"
    },
    {
        "nama" : "Minyak",
        "satuan" : "sdm"
    },
    {
        "nama" : "Air",
        "satuan" : "ml"
    },
    {
        "nama" : "Melinjo",
        "satuan" : "gram"
    },
    {
        "nama" : "Kacang Tanah",
        "satuan" : "gram"
    },
    {
        "nama" : "Jagung Manis",
        "satuan" : "buah"
    },
    {
        "nama" : "Labu Siam",
        "satuan" : "buah"
    },
    {
        "nama" : "Kacang Panjang",
        "satuan" : "gram"
    },
    {
        "nama" : "Royco Bumbu Komplit Sayur Asem",
        "satuan" : "bungkus"
    },
    {
        "nama" : "Daun Melinjo",
        "satuan" : "gram"
    }
]